<Lems>

<!-- Specify which component to run -->
<Target component="sim1"/>

<!-- Include core NeuroML2 ComponentType definitions -->
<Include file="Cells.xml"/>
<Include file="Networks.xml"/>
<Include file="Simulation.xml"/>


<Include file="Izh2007One.net.nml"/>
        

<Simulation id="sim1" length="520ms" step="0.0025ms" target="net1">

    
    <Display id="d1" title="RS v" timeScale="1ms" xmin="-50" xmax="570" ymin="-80" ymax="50">
        <Line id ="RS v" quantity="RS_pop[0]/v" scale="1mV"  color="#0000ff" timeScale="1ms"/>
    </Display>
    <Display id="d2" title="RS u" timeScale="1ms" xmin="-50" xmax="570" ymin="-80" ymax="80">
        <Line id ="RS u" quantity="RS_pop[0]/u" scale="1pA"  color="#ff0000" timeScale="1ms"/>
    </Display>
   

    <OutputFile id="of0" fileName="results/RS_One.dat">
        <OutputColumn id="v" quantity="RS_pop[0]/v" />
        <OutputColumn id="u" quantity="RS_pop[0]/u" />
    </OutputFile>
      
</Simulation>

</Lems>
